setup.cfg
setup.py
aschedule/__init__.py
aschedule/api.py
aschedule.egg-info/PKG-INFO
aschedule.egg-info/SOURCES.txt
aschedule.egg-info/dependency_links.txt
aschedule.egg-info/top_level.txt