Metadata-Version: 1.1
Name: aschedule
Version: 0.0.1
Summary: schedule your co-routines
Home-page: https://gitlab.com/eightnoteight/aschedule
Author: Srinivas Devaki
Author-email: mr.eightnoteight@gmail.com
License: UNKNOWN
Download-URL: https://gitlab.com/eightnoteight/aschedule/repository/archive.zip?ref=master
Platform: UNKNOWN
